Metadata-Version: 2.1
Name: lpips-jax
Version: 0.1.0
Summary: LPIPS Similarity metric for Jax
Home-page: https://github.com/wilson1yan/lpips-jax
Author: Wilson Yan
Author-email: wilson1.yan@berkeley.edu
License: UNKNOWN
Platform: UNKNOWN
Classifier: Programming Language :: Python :: 3
Classifier: License :: OSI Approved :: BSD License
Classifier: Operating System :: OS Independent
